fifo_dipesh_git/fifo_dipesh_git.srcs/sources_1/new/design.v
`timescale 1ns / 1ps
//////////////////////////////////////////////////////////////////////////////////
// Company: 
// Engineer: Aditya Kumar Gupta
// 
// Create Date: 08/14/2022 03:26:38 PM
// Design Name: FIFO
// Module Name: 
// Project Name: FIFO
// Target Devices: 
// Tool Versions: 
// Description: 
// 
// Dependencies: 
// 
// Revision:
// Revision 0.01 - File Created
// Additional Comments:
// 
//////////////////////////////////////////////////////////////////////////////////


module fifo( reset, clk, read_n , write_n ,  data_in, data_out , full , empty, invalid );

input reset, clk, read_n , write_n;
output  full, empty;
output reg invalid;
input [7: 0] data_in;
output reg  [7:0] data_out ;

reg [7:0] mem [15:0];
reg [3:0] wr_pointer, rd_pointer ;
integer i;

assign full = (wr_pointer==15);
assign empty = (wr_pointer==0);
//assign invalid =  full & empty;


always @(posedge clk) begin
    if(reset)
        begin
            for ( i=0;i<16;i=i+1) mem[i] =0;
            rd_pointer=0;
            wr_pointer=0;
            data_out=0;
            invalid=0;
        end
    else if (read_n && !empty) 
        begin
            data_out <= mem [rd_pointer];
            rd_pointer<= rd_pointer+1;
            invalid=0;          
        end
    else if (write_n && !full) 
        begin
            mem [wr_pointer]<=data_in ;
            wr_pointer<= wr_pointer+1;
            invalid=0;
        end
    else invalid=1;
end
endmodule

fifo_dipesh_git/fifo_dipesh_git.srcs/sim_1/new/fifo_tb.sv
//`include "design.v"

module test;
reg reset, clk, read_n , write_n;
wire  full, empty, invalid;
reg [7: 0] data_in;
wire  [7:0] data_out ;

fifo dut1( reset, clk, read_n , write_n ,  data_in, data_out , full , empty, invalid );    

always #5 clk=!clk;

initial begin
    $dumpfile("f.vcd");
    $dumpvars(0);
    rst;
    read;
    write(3);
    write(6);
    read;
    read;
    write(13);
    write(4);
    write(5);
    write(8);
    write(2);
    write(9);
    write(1);
    write(5);
    write(9);
    write(0);
    write(6);
    write(7);
    write(9);
    write(2);
    write(4);
    repeat(15)
    read;
    #10;
    $finish;
end


task initialise;
    begin
        @(negedge clk)
        clk=0;   
    end
endtask

task rst;
    begin
        clk=0;
        @(negedge clk) reset =1;
        write_n=0;
        read_n=0;
        @(negedge clk);
        reset =0;
    end
    
endtask

task read;
    begin
        read_n=1;
        @(posedge clk) ;
        #3 read_n=0;
    end

endtask

task write (input [7:0] wr_data);
    begin
        write_n=1;
        data_in =wr_data;
        @(posedge clk);
        #3;
        write_n=0;
     end
endtask


endmodule

fifo_dipesh_git/fifo_dipesh_git.sim/sim_1/behav/xsim/f.vcd
$date
   Sun Aug 14 18:43:06 2022
$end
$version
  2022.1
$end
$timescale
  1ps
$end
$scope module test $end
$var reg 1 ! reset $end
$var reg 1 " clk $end
$var reg 1 # read_n $end
$var reg 1 $ write_n $end
$var wire 1 % full $end
$var wire 1 & empty $end
$var wire 1 ' invalid $end
$var reg 8 ( data_in [7:0] $end
$var wire 8 ) data_out [7:0] $end
$scope module dut1 $end
$var wire 1 * reset $end
$var wire 1 + clk $end
$var wire 1 , read_n $end
$var wire 1 - write_n $end
$var wire 1 % full $end
$var wire 1 & empty $end
$var reg 1 . invalid $end
$var wire 8 / data_in [7:0] $end
$var reg 8 0 data_out [7:0] $end
$var reg 4 1 wr_pointer [3:0] $end
$var reg 4 2 rd_pointer [3:0] $end
$var integer 32 3 i [31:0] $end
$upscope $end
$scope task rst $end
$upscope $end
$scope task read $end
$upscope $end
$scope task write $end
$var reg 8 4 wr_data [7:0] $end
$upscope $end
$upscope $end
$enddefinitions $end
#0
$dumpvars
x!
0"
x#
x$
x%
x&
x'
bx (
bx )
x*
0+
x,
x-
x.
bx /
bx 0
bx 1
bx 2
bx 3
bx 4
$end
#5000
1"
1'
1+
1.
#10000
1!
0"
0#
0$
1*
0+
0,
0-
#15000
1"
0%
1&
0'
b0 )
1+
0.
b0 0
b0 1
b0 2
b10000 3
#20000
0!
0"
1#
0*
0+
1,
#25000
1"
1'
1+
1.
#28000
0#
1$
b11 (
0,
1-
b11 /
b11 4
#30000
0"
0+
#35000
1"
0%
0&
0'
1+
0.
b1 1
#38000
1$
b110 (
1-
b110 /
b110 4
#40000
0"
0+
#45000
1"
0%
0&
1+
0.
b10 1
#48000
1#
0$
1,
0-
#50000
0"
0+
#55000
1"
b11 )
1+
0.
b11 0
b1 2
#58000
1#
1,
#60000
0"
0+
#65000
1"
b110 )
1+
0.
b110 0
b10 2
#68000
0#
1$
b1101 (
0,
1-
b1101 /
b1101 4
#70000
0"
0+
#75000
1"
0%
0&
1+
0.
b11 1
#78000
1$
b100 (
1-
b100 /
b100 4
#80000
0"
0+
#85000
1"
0%
0&
1+
0.
b100 1
#88000
1$
b101 (
1-
b101 /
b101 4
#90000
0"
0+
#95000
1"
0%
0&
1+
0.
b101 1
#98000
1$
b1000 (
1-
b1000 /
b1000 4
#100000
0"
0+
#105000
1"
0%
0&
1+
0.
b110 1
#108000
1$
b10 (
1-
b10 /
b10 4
#110000
0"
0+
#115000
1"
0%
0&
1+
0.
b111 1
#118000
1$
b1001 (
1-
b1001 /
b1001 4
#120000
0"
0+
#125000
1"
0%
0&
1+
0.
b1000 1
#128000
1$
b1 (
1-
b1 /
b1 4
#130000
0"
0+
#135000
1"
0%
0&
1+
0.
b1001 1
#138000
1$
b101 (
1-
b101 /
b101 4
#140000
0"
0+
#145000
1"
0%
0&
1+
0.
b1010 1
#148000
1$
b1001 (
1-
b1001 /
b1001 4
#150000
0"
0+
#155000
1"
0%
0&
1+
0.
b1011 1
#158000
1$
b0 (
1-
b0 /
b0 4
#160000
0"
0+
#165000
1"
0%
0&
1+
0.
b1100 1
#168000
1$
b110 (
1-
b110 /
b110 4
#170000
0"
0+
#175000
1"
0%
0&
1+
0.
b1101 1
#178000
1$
b111 (
1-
b111 /
b111 4
#180000
0"
0+
#185000
1"
0%
0&
1+
0.
b1110 1
#188000
1$
b1001 (
1-
b1001 /
b1001 4
#190000
0"
0+
#195000
1"
1%
0&
1+
0.
b1111 1
#198000
1$
b10 (
1-
b10 /
b10 4
#200000
0"
0+
#205000
1"
1'
1+
1.
#208000
1$
b100 (
1-
b100 /
b100 4
#210000
0"
0+
#215000
1"
1+
1.
#218000
1#
0$
1,
0-
#220000
0"
0+
#225000
1"
0'
b1101 )
1+
0.
b1101 0
b11 2
#228000
1#
1,
#230000
0"
0+
#235000
1"
b100 )
1+
0.
b100 0
b100 2
#238000
1#
1,
#240000
0"
0+
#245000
1"
b101 )
1+
0.
b101 0
b101 2
#248000
1#
1,
#250000
0"
0+
#255000
1"
b1000 )
1+
0.
b1000 0
b110 2
#258000
1#
1,
#260000
0"
0+
#265000
1"
b10 )
1+
0.
b10 0
b111 2
#268000
1#
1,
#270000
0"
0+
#275000
1"
b1001 )
1+
0.
b1001 0
b1000 2
#278000
1#
1,
#280000
0"
0+
#285000
1"
b1 )
1+
0.
b1 0
b1001 2
#288000
1#
1,
#290000
0"
0+
#295000
1"
b101 )
1+
0.
b101 0
b1010 2
#298000
1#
1,
#300000
0"
0+
#305000
1"
b1001 )
1+
0.
b1001 0
b1011 2
#308000
1#
1,
#310000
0"
0+
#315000
1"
b0 )
1+
0.
b0 0
b1100 2
#318000
1#
1,
#320000
0"
0+
#325000
1"
b110 )
1+
0.
b110 0
b1101 2
#328000
1#
1,
#330000
0"
0+
#335000
1"
b111 )
1+
0.
b111 0
b1110 2
#338000
1#
1,
#340000
0"
0+
#345000
1"
b1001 )
1+
0.
b1001 0
b1111 2
#348000
1#
1,
#350000
0"
0+
#355000
1"
b0 )
1+
0.
b0 0
b0 2
#358000
1#
1,
#360000
0"
0+
#365000
1"
b11 )
1+
0.
b11 0
b1 2
#368000
0#
0,
#370000
0"
0+
#375000
1"
1'
1+
1.
